couchformation/__init__.py
couchformation/aws/__init__.py
couchformation/aws/driver/__init__.py
couchformation/aws/driver/base.py
couchformation/aws/driver/constants.py
couchformation/aws/driver/cost.py
couchformation/aws/driver/dns.py
couchformation/aws/driver/gateway.py
couchformation/aws/driver/image.py
couchformation/aws/driver/instance.py
couchformation/aws/driver/machine.py
couchformation/aws/driver/network.py
couchformation/aws/driver/nsg.py
couchformation/aws/driver/route.py
couchformation/aws/driver/sshkey.py
couchformation/aws/network.py
couchformation/aws/node.py
couchformation/azure/__init__.py
couchformation/azure/driver/__init__.py
couchformation/azure/driver/base.py
couchformation/azure/driver/constants.py
couchformation/azure/driver/disk.py
couchformation/azure/driver/dns.py
couchformation/azure/driver/image.py
couchformation/azure/driver/instance.py
couchformation/azure/driver/machine.py
couchformation/azure/driver/network.py
couchformation/azure/driver/private_dns.py
couchformation/azure/network.py
couchformation/azure/node.py
couchformation/capella/__init__.py
couchformation/capella/driver/__init__.py
couchformation/capella/driver/base.py
couchformation/capella/node.py
couchformation/certificates.py
couchformation/cli/__init__.py
couchformation/cli/cli.py
couchformation/cli/cloudmgr.py
couchformation/cli/dbdump.py
couchformation/config.py
couchformation/constants.py
couchformation/data/build_profiles.yaml
couchformation/data/cloud_profiles.yaml
couchformation/data/container_profiles.yaml
couchformation/data/node_ports.yaml
couchformation/data/node_profiles.yaml
couchformation/data/option_help.yaml
couchformation/data/provisioner_profiles.yaml
couchformation/data/strategy_profiles.yaml
couchformation/data/target_profiles.yaml
couchformation/deployment.py
couchformation/docker/__init__.py
couchformation/docker/driver/__init__.py
couchformation/docker/driver/base.py
couchformation/docker/driver/constants.py
couchformation/docker/driver/container.py
couchformation-4.0.2.dist-info/LICENSE.txt
couchformation-4.0.2.dist-info/METADATA
couchformation-4.0.2.dist-info/WHEEL
couchformation-4.0.2.dist-info/entry_points.txt
couchformation-4.0.2.dist-info/RECORD
