Metadata-Version: 2.1
Name: couchformation
Version: 4.0.2
Summary: Couchbase Cloud Automation
Keywords: couchbase,devops,automation
Author: Michael Minichino
Author-email: info@unix.us.com
Requires-Python: >=3.8,<4
Classifier: Development Status :: 5 - Production/Stable
Classifier: Intended Audience :: Developers
Classifier: License :: OSI Approved :: Apache Software License
Classifier: Operating System :: OS Independent
Classifier: Programming Language :: Python
Classifier: Programming Language :: Python :: 3
Classifier: Programming Language :: Python :: 3.8
Classifier: Programming Language :: Python :: 3.9
Classifier: Programming Language :: Python :: 3.10
Classifier: Programming Language :: Python :: 3.11
Classifier: Programming Language :: Python :: 3.12
Classifier: Programming Language :: Python :: 3.13
Classifier: Topic :: Database
Classifier: Topic :: Software Development :: Libraries
Classifier: Topic :: Software Development :: Libraries :: Python Modules
Requires-Dist: Jinja2 (>=3.0.0)
Requires-Dist: PyYAML (!=6.0.0,!=5.4.0,!=5.4.1)
Requires-Dist: aiohttp (>=3.9.3)
Requires-Dist: attrs (>=23.1.0)
Requires-Dist: azure-common (>=1.1.28)
Requires-Dist: azure-core (>=1.29.6)
Requires-Dist: azure-identity (>=1.12.0)
Requires-Dist: azure-mgmt-compute (>=31.0.0)
Requires-Dist: azure-mgmt-core (>=1.4.0)
Requires-Dist: azure-mgmt-dns (>=8.1.0)
Requires-Dist: azure-mgmt-network (>=25.3.0)
Requires-Dist: azure-mgmt-privatedns (>=1.1.0)
Requires-Dist: azure-mgmt-resource (>=23.1.1)
Requires-Dist: boto3 (>=1.34.17)
Requires-Dist: botocore (>=1.34.17)
Requires-Dist: cryptography (>=42.0.7)
Requires-Dist: dnspython (>=2.1.0)
Requires-Dist: docker (>=6.1.3)
Requires-Dist: google-api-core (>=2.4.0)
Requires-Dist: google-api-python-client (>=2.34.0)
Requires-Dist: google-auth (>=2.3.3)
Requires-Dist: google-auth-httplib2 (>=0.1.0)
Requires-Dist: google-cloud (>=0.34.0)
Requires-Dist: google-cloud-compute (>=1.6.1)
Requires-Dist: google-cloud-dns (>=0.35.0)
Requires-Dist: google-cloud-network-management (>=1.5.4)
Requires-Dist: google-cloud-resource-manager (>=1.12.5)
Requires-Dist: google-cloud-storage (>=2.10.0)
Requires-Dist: googleapis-common-protos (>=1.54.0)
Requires-Dist: libcapella (>=1.0.20)
Requires-Dist: overrides (>=7.4.0)
Requires-Dist: paramiko (>=3.4.0)
Requires-Dist: passlib (>=1.7.4)
Requires-Dist: ply (>=3.11)
Requires-Dist: psutil (>=5.9.5)
Requires-Dist: pycryptodome (>=3.20.0)
Requires-Dist: pytz (>=2021.3)
Requires-Dist: pyvmomi (>=8.0.0.1.1)
Requires-Dist: pywinrm (>=0.4.3)
Requires-Dist: requests (>=2.31.0)
Requires-Dist: rsa (>=4.9)
Requires-Dist: six (>=1.16.0)
Requires-Dist: sqlite-utils (>=3.11)
Requires-Dist: urllib3 (>=1.26.16)
Project-URL: Changelog, https://github.com/couchbaselabs/couch-formation-core/blob/main/CHANGELOG.md
Project-URL: Homepage, https://github.com/couchbaselabs/couch-formation-core
